nordvpn_connect/__init__.py
nordvpn_connect/nordvpn_connect.py
nordvpn_connect/NordVPN_options/countrylist.txt
nordvpn_connect/NordVPN_options/options_linux.txt
nordvpn_connect-0.0.7.dist-info/LICENSE
nordvpn_connect-0.0.7.dist-info/METADATA
nordvpn_connect-0.0.7.dist-info/WHEEL
nordvpn_connect-0.0.7.dist-info/top_level.txt
nordvpn_connect-0.0.7.dist-info/RECORD
