Metadata-Version: 2.1
Name: nordvpn-connect
Version: 0.0.7
Summary: A Python library to connect to NordVPN, works on Windows and Linux
Home-page: https://github.com/sorasful/nordvpn-connect
Author: Sorasful
Author-email: 
License: MIT
Platform: UNKNOWN
Requires-Dist: psutil (==5.7.2)
Requires-Dist: requests (==2.24.0)
Requires-Dist: loguru (==0.5.3)
